pika_utils/__init__.py
pika_utils/_logging.py
pika_utils/blocking.py
pika_utils/job.py
etna_pika_utils-1.3.0.dist-info/LICENSE
etna_pika_utils-1.3.0.dist-info/METADATA
etna_pika_utils-1.3.0.dist-info/WHEEL
etna_pika_utils-1.3.0.dist-info/top_level.txt
etna_pika_utils-1.3.0.dist-info/RECORD
